tornado_wtforms/__init__.py
tornado_wtforms/form.py
tornado_wtforms/i18n.py
tornado_wtforms/meta.py
wtforms_tornado/__init__.py
wtforms_tornado/form.py
tornado_wtforms-0.0.1.dist-info/METADATA
tornado_wtforms-0.0.1.dist-info/WHEEL
tornado_wtforms-0.0.1.dist-info/top_level.txt
tornado_wtforms-0.0.1.dist-info/RECORD
