Metadata-Version: 2.1
Name: tornado-wtforms
Version: 0.0.1
Summary: WTForms extensions for Tornado fork.
Home-page: https://github.com/candango/tornado-wtforms
Author: Flávio Gonçalves Garcia
Author-email: piraz@candango.org
License: Apache License V2.0
Platform: UNKNOWN
Classifier: Development Status :: 4 - Beta
Classifier: Environment :: Console
Classifier: Environment :: Web Environment
Classifier: Intended Audience :: Developers
Classifier: Intended Audience :: System Administrators
Classifier: Programming Language :: Python :: 3
Classifier: Programming Language :: Python :: 3.6
Classifier: Programming Language :: Python :: 3.7
Classifier: Programming Language :: Python :: 3.8
Classifier: Programming Language :: Python :: 3.9
Classifier: Programming Language :: Python :: 3 :: Only
Classifier: Topic :: Internet :: WWW/HTTP :: Dynamic Content
Classifier: Topic :: Software Development :: Libraries
Classifier: Topic :: Software Development :: Libraries :: Python Modules
Requires-Dist: tornado (>=6.1)
Requires-Dist: wtforms
